{
    "name": "Crema Ice Minimal",
    "tokenColors": [
        {
            "scope": [
                "storage.type.contract",
                "storage.modifier.is",
                "storage.type.modifier.access",
                "storage.type.constructor",
                "storage.type.function",
                "storage.type.modifier.extendedscope",
                "variable.language.super",
                // "support.type.primitive",
            ],
            "settings": {
                "foreground": "#A100C0"
            }
        },
        {
            "scope": [
                "comment",
                "punctuation.definition.comment",
                "punctuation.definition.block.tag.jsdoc"
            ],
            "settings": {
                "foreground": "#747474"
            }
        },
        {
            "scope": [
                "string.regexp punctuation.definition.string.begin",
                "string.regexp punctuation.definition.string.end",
                "string.unquoted.go.sum"
            ],
            "settings": {
                "foreground": "#333333"
            }
        },
        {
            "scope": [
                "constant.numeric",
                "string.quoted",
                "string.template",
                "string.unquoted",
                "punctuation.definition.string",
                "string.other",
                "markup.inline.raw.string.markdown",
                "markup.raw.block.markdown",
                "constant.other.character-class.regexp",
                "constant.other.character-class.range.regexp",
                "punctuation.definition.constant.css",
                "constant.character.escape.python"
            ],
            "settings": {
                "foreground": "#A52A0F"
            }
        },
        {
            "scope": [
                "constant.numeric"
            ],
            "settings": {
                "foreground": "#A52A0F"
            }
        },
        {
            "scope": [
                "source",
                "text",
                "variable.other.readwrite",
                "keyword.operator",
                "keyword.control.anchor.regexp",
                "keyword.other.js",
                "keyword.other.ts",
                "meta.embedded",
                "punctuation",
                "entity.name.tag.yaml",
                "keyword.control.flow.block-scalar.folded.yaml",
                "keyword.control.flow.block-scalar.literal.yaml",
                "variable.other.anchor.yaml",
                "variable.other.alias.yaml",
                "variable.other.makefile",
                "variable.other.normal.shell",
                "constant.other.option",
                "string.unquoted.argument.shell",
                "punctuation.definition.string.heredoc.delimiter.shell",
                "string.unquoted.go.mod",
                "string.quoted.double.dockerfile",
                "string.regexp",
                "variable.parameter.positional.shell"
            ],
            "settings": {
                "foreground": "#333333",
                "fontStyle": ""
            }
        },
        {
            "scope": [
                "keyword",
                "entity.name.tag",
                "keyword.other",
                "constant.language.json",
                "punctuation.definition.keyword",
                // "punctuation.definition.template-expression.begin.ts",
                // "punctuation.definition.template-expression.begin.js",
                // "punctuation.definition.template-expression.end.ts",
                // "punctuation.definition.template-expression.end.js",
                "storage.type.function.shell",
                "constant.language.boolean.toml"
            ],
            "settings": {
                "foreground": "#A100C0",
            }
        },
        // -- PYTHON --
        {
            "scope": [
                // "keyword.control.flow.python",
                "constant.language.python",
                "storage.type.function.python",
                "storage.modifier.declaration.python",
                "storage.type.class.python",
                "storage.type.function.async.python",
                "storage.type.function.lambda.python",
                "keyword.operator.logical.python",
            ],
            "settings": {
                "foreground": "#A100C0",
            }
        },
        // -- TYPESCRIPT --
        {
            "scope": [
                "constant.language.undefined.ts",
                // "support.type.object.module.ts",
                "keyword.operator.expression.import.ts",
                "storage.type.ts",
                "storage.type.interface.ts",
                "storage.type.class.ts",
                "storage.type.enum.ts",
                "storage.type.type.ts",
                "storage.type.var.ts",
                "storage.type.let.ts",
                "storage.type.const.ts",
                "storage.type.namespace.ts",
                "storage.type.function.ts",
                "storage.modifier.ts",
                "keyword.other.debugger.ts",
                "keyword.operator.new.ts",
                "variable.language.super.ts",
                "variable.language.this.ts",
                "storage.modifier.async.ts",
                "support.type.builtin.ts",
                "constant.language.null.ts",
                // "support.type.primitive.ts",
                "constant.language.boolean.true.ts",
                "constant.language.boolean.false.ts",
                "keyword.operator.expression.keyof.ts",
                "keyword.operator.type.asserts.ts",
                "keyword.operator.expression.is.ts",
                "keyword.operator.expression.typeof.ts",
                "keyword.operator.expression.delete.ts",
                "keyword.operator.expression.void.ts",
                "keyword.operator.expression.instanceof.ts",
                "keyword.operator.expression.in.ts",
                "keyword.operator.expression.of.ts",
                "keyword.operator.expression.infer.ts",
                "storage.type.property.ts"
            ],
            "settings": {
                "foreground": "#A100C0",
            }
        },
        // -- JAVASCRIPT --
        {
            "scope": [
                "constant.language.undefined.js",
                "storage.modifier.js",
                // "support.type.object.module.js",
                "keyword.operator.expression.import.js",
                "storage.type.js",
                "storage.type.type.js",
                "storage.type.class.js",
                "storage.type.var.js",
                "storage.type.let.js",
                "storage.type.const.js",
                "storage.type.function.js",
                "keyword.other.debugger.js",
                "keyword.operator.new.js",
                "variable.language.super.js",
                "variable.language.this.js",
                "storage.modifier.async.js",
                "support.type.builtin.js",
                "constant.language.null.js",
                // "support.type.primitive.js",
                "constant.language.boolean.true.js",
                "constant.language.boolean.false.js",
                "keyword.operator.expression.keyof.js",
                "keyword.operator.type.asserjs.js",
                "keyword.operator.expression.is.js",
                "keyword.operator.expression.typeof.js",
                "keyword.operator.expression.delete.js",
                "keyword.operator.expression.void.js",
                "keyword.operator.expression.instanceof.js",
                "keyword.operator.expression.in.js",
                "keyword.operator.expression.of.js",
                "keyword.operator.expression.infer.js",
                "storage.type.property.js"
            ],
            "settings": {
                "foreground": "#A100C0",
            }
        },
        // -- CSS & HTML & XML --
        {
            "scope": [
                "variable.parameter.url.css",
                // "punctuation.attribute-shorthand.bind.html"
            ],
            "settings": {
                "foreground": "#A52A0F"
            }
        },
        {
            "scope": [
                "constant.other.color.rgb-value.hex.css",
                "keyword.other.unit.percentage.css",
                "keyword.other.unit.deg.css",
                "keyword.other.unit.px.css",
                "constant.other.unicode-range.css",
                "entity.other.attribute-name.class.css",
                "entity.other.attribute-name.id.css",
                "entity.other.attribute-name.id.css punctuation",
                "constant.character.entity.numeric.hexadecimal.html",
                "constant.character.entity.named.Alpha.html",
                "constant.character.entity.named.nbsp.html",
                "punctuation.definition.entity.html",
                "constant.character.entity.xml",
                "punctuation.definition.constant.xml"
            ],
            "settings": {
                "foreground": "#A52A0F"
            }
        },
        {
            "scope": [
                "keyword.control.at-rule.media.css punctuation.definition.keyword",
                "keyword.control.at-rule.media.css",
                "entity.name.tag.wildcard.css"
            ],
            "settings": {
                "foreground": "#333333"
            }
        },
        
        // -- SQL --
        {
            "scope": [
                "storage.modifier.sql",
                "support.function.aggregate.sql"
            ],
            "settings": {
                "foreground": "#A100C0",
            }
        },
        // -- YAML --
        {
            "scope": [
                "constant.language.boolean.yaml"
            ],
            "settings": {
                "foreground": "#A100C0",
            }
        },
        // -- MAKEFILE
        {
            "scope": [
                "string.interpolated.makefile",
                "keyword.control.@.makefile"
            ],
            "settings": {
                "foreground": "#333333"
            }
        },
        // -- MARKDOWN
        {
            "scope": [
                "markup.bold"
            ],
            "settings": {
                "foreground": "#A100C0",
                "fontStyle": "bold"
            }
        },
        {
            "scope": [
                "markup.italic"
            ],
            "settings": {
                "foreground": "#A100C0",
                "fontStyle": "italic"
            }
        },
        {
            "scope": [
                "markup.strikethrough"
            ],
            "settings": {
                "foreground": "#A100C0",
                "fontStyle": "strikethrough"
            }
        },
        {
            "scope": [
                "markup.heading",
                "punctuation.definition.heading.markdown",
                "punctuation.definition.list.begin.markdown",
            ],
            "settings": {
                "foreground": "#A100C0",
            }
        },
        {
            "scope": [
                "markup.underline.link"
            ],
            "settings": {
                "foreground": "#A300C8"
            }
        },
        {
            "scope": [
                "string.other.link.title.markdown",
                "string.other.link.description.markdown",
                "constant.other.reference.link.markdown"
            ],
            "settings": {
                "foreground": "#C7382C"
            }
        },
        // -- JAVA -- 
        {
            "scope": [
                "storage.modifier.java",
                "storage.modifier.extends.java",
                "constant.language.java",
                "storage.type.primitive.java"
            ],
            "settings": {
                "foreground": "#A100C0",
            }
        },
        // -- GROOVY -- 
        {
            "scope": [
                "storage.modifier.groovy",
                "storage.type.def.groovy",
                "storage.modifier.static.groovy",
                "keyword.operator.in.groovy",
                "storage.modifier.other.groovy"
            ],
            "settings": {
                "foreground": "#A100C0",
            }
        },
        // -- CPP -- 
        {
            "scope": [
                "storage.type.class.cpp",
                "storage.modifier.specifier.static.cpp",
                "storage.type.built-in.primitive.cpp",
                "storage.type.modifier.access.control.public.cpp",
                "storage.modifier.virtual.cpp",
                "storage.type.modifier.final.cpp",
                "storage.type.modifier.access.public.cpp",
                "storage.modifier.specifier.functional.pre-parameters.explicit.cpp",
                "keyword.operator.noexcept.cpp",
                "storage.modifier.specifier.functional.post-parameters.override.cpp",
                "storage.type.modifier.access.control.private.cpp",
                "storage.modifier.specifier.functional.pre-parameters.mutable.cpp",
                "entity.name.operator.cpp",
                "storage.modifier.specifier.functional.post-parameters.noexcept.cpp",
                "storage.type.enum.cpp",
                "storage.type.struct.cpp",
                "storage.modifier.inline.cpp",
                "storage.modifier.specifier.thread_local.cpp",
                "storage.type.enum.enum-key.class.cpp",
                "support.type.built-in.posix-reserved.cpp",
                "storage.modifier.specifier.volatile.cpp",
                "storage.modifier.specifier.register.cpp",
                "storage.modifier.constexpr.cpp",
                "keyword.operator.cast.static_cast.cpp",
                "keyword.operator.cast.reinterpret_cast.cpp",
                "keyword.operator.cast.const_cast.cpp",
                "keyword.operator.cast.dynamic_cast.cpp",
                "constant.language.nullptr.cpp",
                "keyword.operator.alignas.cpp",
                "keyword.operator.alignof.cpp",
                "storage.modifier.specifier.const.cpp",
                "constant.language.false.cpp",
                "constant.language.true.cpp",
                "keyword.operator.and.cpp",
                "keyword.operator.not.cpp",
                "keyword.operator.or.cpp",
                "keyword.operator.and_eq.cpp",
                "keyword.operator.or_eq.cpp",
                "keyword.operator.xor.cpp",
                "keyword.operator.xor_eq.cpp",
                "keyword.operator.not_eq.cpp",
                "keyword.operator.sizeof.cpp",
                "storage.type.extern.cpp",
                "punctuation.definition.directive.cpp"
            ],
            "settings": {
                "foreground": "#A100C0",
            }
        },
        // -- C -- 
        {
            "scope": [
                "storage.modifier.c",
                "storage.type.built-in.primitive.c",
                "source.c storage.type",
                "keyword.operator.sizeof.c",
                "punctuation.definition.directive.c"
            ],
            "settings": {
                "foreground": "#A100C0",
            }
        },
        // -- C# -- 
        {
            "scope": [
                "storage.type.namespace.cs",
                "source.cs storage.type",
                "storage.modifier.static.cs",
                "keyword.operator.expression.new.cs",
                "source.cs storage.modifier",
                "keyword.operator.expression.await.cs",
                "constant.language.boolean.true.cs",
                "constant.language.boolean.false.cs",
                "keyword.operator.expression.nameof.cs",
                "constant.language.null.cs",
                "variable.language.base.cs",
                "keyword.operator.expression.sizeof.cs",
                "keyword.operator.expression.typeof.cs",
                "keyword.operator.expression.stackalloc.cs",
                "keyword.operator.expression.pattern.is.cs",
                "keyword.operator.expression.as.cs",
            ],
            "settings": {
                "foreground": "#A100C0",
            }
        },
        // -- KOTLIN -- 
        {
            "scope": [
                "storage.modifier.other.kotlin",
                "variable.language.this.kotlin",
                "constant.language.null.kotlin",
            ],
            "settings": {
                "foreground": "#A100C0",
            }
        },
        // -- KOTLIN -- 
        {
            "scope": [
                "storage.modifier.other.kotlin",
                "variable.language.this.kotlin",
                "constant.language.null.kotlin",
            ],
            "settings": {
                "foreground": "#A100C0",
            }
        },
        // -- INI -- 
        {
            "scope": [
                "keyword.other.definition.ini",
                "source.ini string.quoted",
                "source.ini punctuation.definition.string"
            ],
            "settings": {
                "foreground": "#333333"
            }
        },
        {
            "scope": [
                "entity.name.section.group-title.ini",
            ],
            "settings": {
                "foreground": "#A100C0",
            }
        },
        // -- LUA -- 
        {
            "scope": [
                "constant.language.lua",
                "keyword.operator.lua"
            ],
            "settings": {
                "foreground": "#A100C0",
            }
        },
        // -- SWIFT -- 
        {
            "scope": [
                "source.swift storage.modifier",
                "source.swift storage.type",
                "variable.language.swift",
                "constant.language.nil.swift",
                "source.swift constant.language.boolean"
            ],
            "settings": {
                "foreground": "#A100C0",
            }
        },
        // -- OBJECTIVE-C -- 
        {
            "scope": [
                "punctuation.definition.directive.objc",
                "storage.type.objc",
                "punctuation.definition.storage.type.objc",
                "storage.type.built-in.primitive.objc",
                "storage.modifier.objc",
                "constant.language.objc",
                "variable.language.objc"
            ],
            "settings": {
                "foreground": "#A100C0",
            }
        },
        // -- R -- 
        {
            "scope": [
                "constant.language.r",
            ],
            "settings": {
                "foreground": "#A100C0",
            }
        },
        // -- RUBY -- 
        {
            "scope": [
                "constant.language.boolean.ruby",
            ],
            "settings": {
                "foreground": "#A100C0",
            }
        },
        // -- PHP --
        {
            "scope": [
                "source.php storage",
                "source.php support.function.construct",
                "source.php support.function.basic_functions",
                "constant.language.php"
            ],
            "settings": {
                "foreground": "#A100C0",
            }
        },
        {
            "scope": [
                "string.unquoted.heredoc.php punctuation.definition.string",
                "string.unquoted",
                "variable.other.php",
                "source.php string.interpolated.php",
                "string.interpolated.php punctuation.definition.string ",
                "punctuation.definition.string.begin.php string.interpolated.php",
            ],
            "settings": {
                "foreground": "#333333"
            }
        },
        // -- RUST --
        {
            "scope": [
                "storage.type.rust",
                "source.rust storage.modifier"
            ],
            "settings": {
                "foreground": "#A100C0",
            }
        },
    ],
    "colors": {
        "activityBar.activeBackground": "#00000000",
        "activityBar.activeBorder": "#00000000",
        "activityBar.activeFocusBorder": "#747474",
        "activityBar.background": "#E0E0E0",
        "activityBar.border": "#00000000",
        "activityBar.dropBorder": "#33333333",
        "activityBar.foreground": "#333333",
        "activityBar.inactiveForeground": "#888888",
        "activityBarBadge.background": "#ADADAD",
        "activityBarBadge.foreground": "#333333",
        "activityBarTop.activeBorder": "#00000000",
        "activityBarTop.dropBorder": "#33333333",
        "activityBarTop.foreground": "#333333",
        "activityBarTop.inactiveForeground": "#888888",
        "badge.background": "#C0C0C0",
        "badge.foreground": "#333333",
        "banner.background": "#C0C0C0",
        "banner.foreground": "#333333",
        "banner.iconForeground": "#333333",
        "breadcrumb.activeSelectionForeground": "#333333",
        "breadcrumb.background": "#E7E7E7",
        "breadcrumb.focusForeground": "#333333",
        "breadcrumb.foreground": "#333333cc",
        "breadcrumbPicker.background": "#E0E0E0",
        "button.background": "#9C9C9C",
        "button.border": "#00000000",
        "button.foreground": "#333333",
        "button.hoverBackground": "#ADADAD",
        "button.secondaryBackground": "#ADADAD",
        "button.secondaryForeground": "#333333",
        "button.secondaryHoverBackground": "#bfbfbf",
        "button.separator": "#00000000",
        "charts.blue": "#003FE6",
        "charts.foreground": "#333333",
        "charts.green": "#007100",
        "charts.lines": "#494949",
        "charts.orange": "#D85A10",
        "charts.purple": "#8839EF",
        "charts.red": "#C73600",
        "charts.yellow": "#DF8E1D",
        "checkbox.background": "#C0C0C0",
        "checkbox.border": "#00000000",
        "checkbox.foreground": "#333333",
        "commandCenter.activeBackground": "#ADADAD33",
        "commandCenter.activeBorder": "#00000000",
        "commandCenter.activeForeground": "#333333",
        "commandCenter.background": "#E7E7E7",
        "commandCenter.border": "#00000000",
        "commandCenter.foreground": "#494949",
        "commandCenter.inactiveBorder": "#00000000",
        "commandCenter.inactiveForeground": "#494949",
        "debugConsole.errorForeground": "#C73600",
        "debugConsole.infoForeground": "#003FE6",
        "debugConsole.sourceForeground": "#C44300",
        "debugConsole.warningForeground": "#D85A10",
        "debugConsoleInputIcon.foreground": "#333333",
        "debugExceptionWidget.background": "#ECECEC",
        "debugExceptionWidget.border": "#9C9C9C",
        "debugIcon.breakpointCurrentStackframeForeground": "#ADADAD",
        "debugIcon.breakpointDisabledForeground": "#C7360099",
        "debugIcon.breakpointForeground": "#C73600",
        "debugIcon.breakpointStackframeForeground": "#ADADAD",
        "debugIcon.breakpointUnverifiedForeground": "#ba7257",
        "debugIcon.continueForeground": "#007100",
        "debugIcon.disconnectForeground": "#ADADAD",
        "debugIcon.pauseForeground": "#003FE6",
        "debugIcon.restartForeground": "#267A9A",
        "debugIcon.startForeground": "#007100",
        "debugIcon.stepBackForeground": "#ADADAD",
        "debugIcon.stepIntoForeground": "#333333",
        "debugIcon.stepOutForeground": "#333333",
        "debugIcon.stepOverForeground": "#8839EF",
        "debugIcon.stopForeground": "#C73600",
        "debugTokenExpression.boolean": "#8839EF",
        "debugTokenExpression.error": "#C73600",
        "debugTokenExpression.number": "#D85A10",
        "debugTokenExpression.string": "#007100",
        "debugToolBar.background": "#E0E0E0",
        "debugToolBar.border": "#00000000",
        "descriptionForeground": "#333333",
        "diffEditor.border": "#ADADAD",
        "diffEditor.diagonalFill": "#ADADAD99",
        "diffEditor.insertedLineBackground": "#00710026",
        "diffEditor.insertedTextBackground": "#00710033",
        "diffEditor.removedLineBackground": "#C7360026",
        "diffEditor.removedTextBackground": "#C7360033",
        "diffEditorOverview.insertedForeground": "#007100cc",
        "diffEditorOverview.removedForeground": "#C73600cc",
        "disabledForeground": "#5F5F5F",
        "dropdown.background": "#E0E0E0",
        "dropdown.border": "#747474",
        "dropdown.foreground": "#333333",
        "dropdown.listBackground": "#ADADAD",
        "editor.background": "#E7E7E7",
        "editor.findMatchBackground": "#ddb2a2",
        "editor.findMatchBorder": "#C7360033",
        "editor.findMatchHighlightBackground": "#a3d3e6",
        "editor.findMatchHighlightBorder": "#04A5E533",
        "editor.findRangeHighlightBackground": "#a3d3e6",
        "editor.findRangeHighlightBorder": "#04A5E533",
        "editor.focusedStackFrameHighlightBackground": "#00710026",
        "editor.foldBackground": "#003FE624",
        "editor.foreground": "#333333",
        "editor.hoverHighlightBackground": "#04A5E540",
        "editor.lineHighlightBackground": "#33333312",
        "editor.lineHighlightBorder": "#00000000",
        "editor.rangeHighlightBackground": "#33333312",
        "editor.rangeHighlightBorder": "#00000000",
        "editor.selectionBackground": "#7474744d",
        "editor.selectionHighlightBackground": "#74747433",
        "editor.selectionHighlightBorder": "#74747433",
        "editor.stackFrameHighlightBackground": "#DF8E1D26",
        "editor.wordHighlightBackground": "#74747433",
        "editor.wordHighlightStrongBackground": "#003fe626",
        "editorBracketHighlight.foreground1": "#C73600",
        "editorBracketHighlight.foreground2": "#267A9A",
        "editorBracketHighlight.foreground3": "#8839EF",
        "editorBracketHighlight.foreground4": "#D85A10",
        // "editorBracketHighlight.foreground5": "#006BB0",
        // "editorBracketHighlight.foreground6": "#A100C0",
        "editorBracketHighlight.unexpectedBracket.foreground": "#747474",
        "editorBracketMatch.background": "#7474741a",
        "editorBracketMatch.border": "#747474",
        "editorCodeLens.foreground": "#888888",
        // "editorCursor.background": null,
        "editorCursor.foreground": "#333333",
        "editorError.background": "#00000000",
        "editorError.border": "#00000000",
        "editorError.foreground": "#C73600",
        "editorGroup.border": "#D1D1D1",
        "editorGroup.dropBackground": "#33333333",
        "editorGroup.emptyBackground": "#E7E7E7",
        "editorGroupHeader.tabsBackground": "#E0E0E0",
        "editorGutter.addedBackground": "#007100",
        "editorGutter.background": "#E7E7E7",
        "editorGutter.commentGlyphForeground": "#9C9C9C",
        "editorGutter.commentRangeForeground": "#D1D1D1",
        "editorGutter.deletedBackground": "#C73600",
        "editorGutter.foldingControlForeground": "#747474",
        "editorGutter.modifiedBackground": "#003FE6",
        "editorHoverWidget.background": "#E0E0E0",
        "editorHoverWidget.border": "#ADADAD",
        "editorHoverWidget.foreground": "#333333",
        "editorIndentGuide.activeBackground1": "#888888",
        "editorIndentGuide.background1": "#C0C0C0",
        "editorInfo.background": "#00000000",
        "editorInfo.border": "#00000000",
        "editorInfo.foreground": "#003FE6",
        "editorInlayHint.background": "#E0E0E0bf",
        "editorInlayHint.foreground": "#ADADAD",
        "editorInlayHint.parameterBackground": "#E0E0E0bf",
        "editorInlayHint.parameterForeground": "#5F5F5F",
        "editorInlayHint.typeBackground": "#E0E0E0bf",
        "editorInlayHint.typeForeground": "#494949",
        "editorLightBulb.foreground": "#DF8E1D",
        "editorLineNumber.activeForeground": "#333333",
        "editorLineNumber.foreground": "#888888",
        "editorLink.activeForeground": "#9C9C9C",
        "editorMarkerNavigation.background": "#E0E0E0",
        "editorMarkerNavigationError.background": "#C73600",
        "editorMarkerNavigationInfo.background": "#003FE6",
        "editorMarkerNavigationWarning.background": "#D85A10",
        "editorOverviewRuler.background": null,
        "editorOverviewRuler.border": "#00000000",
        "editorOverviewRuler.modifiedForeground": "#003FE6",
        "editorRuler.foreground": "#ADADAD",
        "editorStickyScrollHover.background": "#D1D1D1",
        "editorSuggestWidget.background": "#E0E0E0",
        "editorSuggestWidget.border": "#ADADAD",
        "editorSuggestWidget.foreground": "#333333",
        "editorSuggestWidget.highlightForeground": "#9C9C9C",
        "editorSuggestWidget.selectedBackground": "#D1D1D1",
        "editorWarning.background": "#00000000",
        "editorWarning.border": "#00000000",
        "editorWarning.foreground": "#D85A10",
        "editorWhitespace.foreground": "#74747466",
        "editorWidget.background": "#E0E0E0",
        "editorWidget.foreground": "#333333",
        "editorWidget.resizeBorder": "#ADADAD",
        "errorForeground": "#C73600",
        "extensionBadge.remoteBackground": "#003FE6",
        "extensionBadge.remoteForeground": "#ECECEC",
        "extensionButton.background": "#9C9C9C",
        "extensionButton.foreground": "#333333",
        "extensionButton.hoverBackground": "#ADADAD",
        "extensionButton.prominentBackground": "#9C9C9C",
        "extensionButton.prominentForeground": "#333333",
        "extensionButton.prominentHoverBackground": "#aeaeae",
        "extensionButton.separator": "#E7E7E7",
        "extensionIcon.preReleaseForeground": "#ADADAD",
        "extensionIcon.sponsorForeground": "#A100C0",
        "extensionIcon.starForeground": "#DF8E1D",
        "extensionIcon.verifiedForeground": "#007100",
        "focusBorder": "#747474",
        "foreground": "#333333",
        "gitDecoration.addedResourceForeground": "#007100",
        "gitDecoration.conflictingResourceForeground": "#8839EF",
        "gitDecoration.deletedResourceForeground": "#C73600",
        "gitDecoration.ignoredResourceForeground": "#747474",
        "gitDecoration.modifiedResourceForeground": "#003FE6",
        "gitDecoration.stageDeletedResourceForeground": "#C73600",
        "gitDecoration.stageModifiedResourceForeground": "#003FE6",
        "gitDecoration.submoduleResourceForeground": "#003FE6",
        "gitDecoration.untrackedResourceForeground": "#007100",
        "gitlens.trailingLineForegroundColor": "#888888",
        "icon.foreground": "#333333",
        "input.background": "#D1D1D1",
        "input.border": "#00000000",
        "input.foreground": "#333333",
        "input.placeholderForeground": "#5F5F5F",
        "inputOption.activeBackground": "#ADADAD",
        "inputOption.activeBorder": "#333333",
        "inputOption.activeForeground": "#333333",
        "inputValidation.errorBackground": "#C73600",
        "inputValidation.errorBorder": "#ECECEC33",
        "inputValidation.errorForeground": "#ECECEC",
        "inputValidation.infoBackground": "#003FE6",
        "inputValidation.infoBorder": "#ECECEC33",
        "inputValidation.infoForeground": "#ECECEC",
        "inputValidation.warningBackground": "#D85A10",
        "inputValidation.warningBorder": "#ECECEC33",
        "inputValidation.warningForeground": "#ECECEC",
        "list.activeSelectionBackground": "#D1D1D1",
        "list.activeSelectionForeground": "#333333",
        "list.dropBackground": "#33333333",
        "list.focusBackground": "#E0E0E0",
        "list.focusForeground": "#333333",
        "list.focusOutline": "#747474",
        "list.highlightForeground": "#9C9C9C",
        "list.hoverBackground": "#D1D1D180",
        "list.hoverForeground": "#333333",
        "list.inactiveSelectionBackground": "#D1D1D1",
        "list.inactiveSelectionForeground": "#333333",
        "list.warningForeground": "#D85A10",
        "listFilterWidget.background": "#C0C0C0",
        "listFilterWidget.noMatchesOutline": "#C73600",
        "listFilterWidget.outline": "#00000000",
        "menu.background": "#E7E7E7",
        "menu.border": "#E7E7E780",
        "menu.foreground": "#333333",
        "menu.selectionBackground": "#ADADAD",
        "menu.selectionBorder": "#00000000",
        "menu.selectionForeground": "#333333",
        "menu.separatorBackground": "#ADADAD",
        "menubar.selectionBackground": "#C0C0C0",
        "menubar.selectionForeground": "#333333",
        "merge.commonContentBackground": "#C0C0C0",
        "merge.commonHeaderBackground": "#ADADAD",
        "merge.currentContentBackground": "#00710033",
        "merge.currentHeaderBackground": "#00710066",
        "merge.incomingContentBackground": "#003FE633",
        "merge.incomingHeaderBackground": "#003FE666",
        "minimap.background": "#E7E7E780",
        "minimap.errorHighlight": "#C73600bf",
        "minimap.findMatchHighlight": "#04A5E54d",
        "minimap.selectionHighlight": "#ADADADbf",
        "minimap.selectionOccurrenceHighlight": "#ADADADbf",
        "minimap.warningHighlight": "#D85A10bf",
        "minimapGutter.addedBackground": "#007100bf",
        "minimapGutter.deletedBackground": "#C73600bf",
        "minimapGutter.modifiedBackground": "#003FE6bf",
        "minimapSlider.activeBackground": "#33333399",
        "minimapSlider.background": "#33333333",
        "minimapSlider.hoverBackground": "#33333366",
        "notificationCenter.border": "#00000000",
        "notificationCenterHeader.background": "#E0E0E0",
        "notificationCenterHeader.foreground": "#333333",
        "notificationLink.foreground": "#003FE6",
        "notificationToast.border": "#00000000",
        "notifications.background": "#E0E0E0",
        "notifications.border": "#00000000",
        "notifications.foreground": "#333333",
        "notificationsErrorIcon.foreground": "#C73600",
        "notificationsInfoIcon.foreground": "#003FE6",
        "notificationsWarningIcon.foreground": "#D85A10",
        "panel.background": "#E0E0E0",
        "panel.border": "#E7E7E7",
        "panelSection.border": "#ADADAD",
        "panelSection.dropBackground": "#33333333",
        "panelTitle.activeBorder": "#00000000",
        "panelTitle.activeForeground": "#333333",
        "panelTitle.inactiveForeground": "#747474",
        "peekView.border": "#333333",
        "peekViewEditor.background": "#E0E0E0",
        "peekViewEditor.matchHighlightBackground": "#04A5E54d",
        "peekViewEditor.matchHighlightBorder": "#00000000",
        "peekViewEditorGutter.background": "#E0E0E0",
        "peekViewResult.background": "#E0E0E0",
        "peekViewResult.fileForeground": "#333333",
        "peekViewResult.lineForeground": "#333333",
        "peekViewResult.matchHighlightBackground": "#04A5E54d",
        "peekViewResult.selectionBackground": "#D1D1D1",
        "peekViewResult.selectionForeground": "#333333",
        "peekViewTitle.background": "#E7E7E7",
        "peekViewTitleDescription.foreground": "#494949b3",
        "peekViewTitleLabel.foreground": "#333333",
        "pickerGroup.border": "#333333",
        "pickerGroup.foreground": "#9C9C9C",
        "problemsErrorIcon.foreground": "#C73600",
        "problemsInfoIcon.foreground": "#003FE6",
        "problemsWarningIcon.foreground": "#D85A10",
        "progressBar.background": "#9C9C9C",
        "sash.hoverBorder": "#747474",
        "scrollbar.shadow": "#E0E0E0",
        "scrollbarSlider.activeBackground": "#49494966",
        "scrollbarSlider.background": "#88888866",
        "scrollbarSlider.hoverBackground": "#9C9C9Cb3",
        "selection.background": "#33333366",
        "settings.dropdownBackground": "#C0C0C0",
        "settings.dropdownListBorder": "#00000000",
        "settings.focusedRowBackground": "#ADADAD33",
        "settings.headerForeground": "#333333",
        "settings.modifiedItemIndicator": "#333333",
        "settings.numberInputBackground": "#C0C0C0",
        "settings.numberInputBorder": "#00000000",
        "settings.textInputBackground": "#C0C0C0",
        "settings.textInputBorder": "#00000000",
        "sideBar.background": "#E0E0E0",
        "sideBar.border": "#E7E7E7",
        "sideBar.dropBackground": "#33333333",
        "sideBar.foreground": "#333333",
        "sideBarSectionHeader.background": "#E0E0E0",
        "sideBarSectionHeader.foreground": "#333333",
        "sideBarTitle.foreground": "#333333",
        "statusBar.background": "#E0E0E0",
        "statusBar.border": "#00000000",
        "statusBar.debuggingBackground": "#D1D1D1",
        "statusBar.debuggingBorder": "#00000000",
        "statusBar.debuggingForeground": "#333333",
        "statusBar.foreground": "#333333",
        "statusBar.noFolderBackground": "#E0E0E0",
        "statusBar.noFolderBorder": "#00000000",
        "statusBar.noFolderForeground": "#333333",
        "statusBarItem.activeBackground": "#ADADAD66",
        "statusBarItem.errorBackground": "#00000000",
        "statusBarItem.errorForeground": "#C73600",
        "statusBarItem.hoverBackground": "#ADADAD33",
        "statusBarItem.prominentBackground": "#00000000",
        "statusBarItem.prominentForeground": "#333333",
        "statusBarItem.prominentHoverBackground": "#ADADAD33",
        "statusBarItem.remoteBackground": "#E0E0E0",
        "statusBarItem.remoteForeground": "#333333",
        "statusBarItem.remoteHoverBackground": "#ADADAD33",
        "statusBarItem.warningBackground": "#00000000",
        "statusBarItem.warningForeground": "#D85A10",
        "symbolIcon.arrayForeground": "#D85A10",
        "symbolIcon.booleanForeground": "#8839EF",
        "symbolIcon.classForeground": "#DF8E1D",
        "symbolIcon.colorForeground": "#A100C0",
        "symbolIcon.constantForeground": "#D85A10",
        "symbolIcon.constructorForeground": "#6C64F0",
        "symbolIcon.enumeratorForeground": "#DF8E1D",
        "symbolIcon.enumeratorMemberForeground": "#DF8E1D",
        "symbolIcon.eventForeground": "#A100C0",
        "symbolIcon.fieldForeground": "#333333",
        "symbolIcon.fileForeground": "#333333",
        "symbolIcon.folderForeground": "#333333",
        "symbolIcon.functionForeground": "#003FE6",
        "symbolIcon.interfaceForeground": "#DF8E1D",
        "symbolIcon.keyForeground": "#267A9A",
        "symbolIcon.keywordForeground": "#8839EF",
        "symbolIcon.methodForeground": "#003FE6",
        "symbolIcon.moduleForeground": "#333333",
        "symbolIcon.namespaceForeground": "#DF8E1D",
        "symbolIcon.nullForeground": "#E64553",
        "symbolIcon.numberForeground": "#D85A10",
        "symbolIcon.objectForeground": "#DF8E1D",
        "symbolIcon.operatorForeground": "#267A9A",
        "symbolIcon.packageForeground": "#C7382C",
        "symbolIcon.propertyForeground": "#E64553",
        "symbolIcon.referenceForeground": "#DF8E1D",
        "symbolIcon.snippetForeground": "#C7382C",
        "symbolIcon.stringForeground": "#007100",
        "symbolIcon.structForeground": "#267A9A",
        "symbolIcon.textForeground": "#333333",
        "symbolIcon.typeParameterForeground": "#E64553",
        "symbolIcon.unitForeground": "#333333",
        "symbolIcon.variableForeground": "#333333",
        "tab.activeBackground": "#E7E7E7",
        "tab.activeBorder": "#00000000",
        "tab.activeBorderTop": "#333333",
        "tab.activeForeground": "#333333",
        "tab.activeModifiedBorder": "#003FE6",
        "tab.border": "#E7E7E7",
        "tab.hoverBackground": "#E7E7E7",
        "tab.hoverBorder": "#00000000",
        "tab.hoverForeground": "#333333",
        "tab.inactiveBackground": "#E0E0E0",
        "tab.inactiveForeground": "#747474",
        "tab.inactiveModifiedBorder": "#003FE64d",
        "tab.lastPinnedBorder": "#333333",
        "tab.unfocusedActiveBackground": "#E7E7E7",
        "tab.unfocusedActiveBorder": "#E7E7E7",
        "tab.unfocusedActiveBorderTop": "#00000000",
        "tab.unfocusedActiveForeground": "#333333",
        "tab.unfocusedInactiveBackground": "#E0E0E0",
        "tab.unfocusedInactiveForeground": "#747474",
        "tab.unfocusedHoverBackground": "#E7E7E7",
        "tab.unfocusedHoverForeground": "#333333",
        "terminal.ansiBlack": "#5C5F77",
        "terminal.ansiBlue": "#1E66F5",
        "terminal.ansiBrightBlack": "#6C6F85",
        "terminal.ansiBrightBlue": "#456EFF",
        "terminal.ansiBrightCyan": "#2D9FA8",
        "terminal.ansiBrightGreen": "#49AF3D",
        "terminal.ansiBrightMagenta": "#FE85D8",
        "terminal.ansiBrightRed": "#DE293E",
        "terminal.ansiBrightWhite": "#BCC0CC",
        "terminal.ansiBrightYellow": "#EEA02D",
        "terminal.ansiCyan": "#179299",
        "terminal.ansiGreen": "#40A02B",
        "terminal.ansiMagenta": "#EA76CB",
        "terminal.ansiRed": "#D20F39",
        "terminal.ansiWhite": "#ACB0BE",
        "terminal.ansiYellow": "#DF8E1D",
        "terminal.border": "#ADADAD",
        "terminal.dropBackground": "#33333333",
        "terminal.foreground": "#333333",
        "terminal.inactiveSelectionBackground": "#ADADAD80",
        "terminal.selectionBackground": "#ADADAD",
        "terminal.tab.activeBorder": "#333333",
        "terminalCommandDecoration.defaultBackground": "#ADADAD",
        "terminalCommandDecoration.errorBackground": "#C73600",
        "terminalCommandDecoration.successBackground": "#007100",
        // "terminalCursor.background": null,
        "terminalCursor.foreground": "#333333",
        "terminalOverviewRuler.border": "#00000000",
        "testing.coverCountBadgeBackground": "#00000000",
        "testing.coverCountBadgeForeground": "#9C9C9C",
        "testing.coveredBackground": "#0071004d",
        "testing.coveredBorder": "#00000000",
        "testing.coveredGutterBackground": "#0071004d",
        "testing.iconErrored": "#C73600",
        "testing.iconErrored.retired": "#C73600",
        "testing.iconFailed": "#C73600",
        "testing.iconFailed.retired": "#C73600",
        "testing.iconPassed": "#007100",
        "testing.iconPassed.retired": "#007100",
        "testing.iconQueued": "#003FE6",
        "testing.iconQueued.retired": "#003FE6",
        "testing.iconSkipped": "#5F5F5F",
        "testing.iconSkipped.retired": "#5F5F5F",
        "testing.iconUnset": "#333333",
        "testing.iconUnset.retired": "#333333",
        "testing.message.error.lineBackground": "#C7360026",
        "testing.message.info.decorationForeground": "#007100cc",
        "testing.message.info.lineBackground": "#00710026",
        "testing.messagePeekBorder": "#9C9C9C",
        "testing.messagePeekHeaderBackground": "#ADADAD",
        "testing.peekBorder": "#9C9C9C",
        "testing.peekHeaderBackground": "#ADADAD",
        "testing.runAction": "#9C9C9C",
        "testing.uncoveredBackground": "#C7360033",
        "testing.uncoveredBorder": "#00000000",
        "testing.uncoveredBranchBackground": "#C7360033",
        "testing.uncoveredGutterBackground": "#C7360040",
        "textBlockQuote.background": "#E0E0E0",
        "textBlockQuote.border": "#ECECEC",
        "textCodeBlock.background": "#E0E0E0",
        "textLink.activeForeground": "#C7382C",
        "textLink.foreground": "#A300C8",
        "textPreformat.foreground": "#333333",
        "textSeparator.foreground": "#333333",
        "titleBar.activeBackground": "#E0E0E0",
        "titleBar.activeForeground": "#333333",
        "titleBar.border": "#00000000",
        "titleBar.inactiveBackground": "#E0E0E0",
        "titleBar.inactiveForeground": "#33333380",
        "tree.inactiveIndentGuidesStroke": "#ADADAD66",
        "tree.indentGuidesStroke": "#ADADAD",
        "walkThrough.embeddedEditorBackground": "#E7E7E74d",
        "welcomePage.progress.background": "#ECECEC",
        "welcomePage.progress.foreground": "#9C9C9C",
        "welcomePage.tileBackground": "#E0E0E0",
        "widget.shadow": "#E0E0E080",
        // "window.activeBorder": "#00000000",
        // "window.inactiveBorder": "#00000000",
        //"actionBar.toggledBackground": "#ADADAD",
        //"activityErrorBadge.background": "#f14c4c",
        //"activityErrorBadge.foreground": "#000000",
        //"activityWarningBadge.background": "#cca700",
        //"activityWarningBadge.foreground": "#000000",
        //"chart.axis": "#bfbfbf66",
        //"chart.guide": "#bfbfbf33",
        //"chart.line": "#236b8e",
        //"chat.avatarBackground": "#E7E7E7",
        //"chat.avatarForeground": "#333333",
        //"chat.editedFileForeground": "#DF8E1D",
        //"chat.requestBackground": "#E7E7E79e",
        //"chat.requestBorder": "#ffffff1a",
        //"chat.slashCommandBackground": "#34414b8f",
        //"chat.slashCommandForeground": "#40a6ff",
        //"checkbox.selectBackground": "#E0E0E0",
        //"checkbox.selectBorder": "#333333",
        //"commandCenter.debuggingBackground": "#D1D1D142",
        //"commentsView.resolvedIcon": "#5F5F5F",
        //"commentsView.unresolvedIcon": "#00000000",
        //"debugTokenExpression.name": "#A100C0",
        //"debugTokenExpression.type": "#4a90e2",
        //"debugTokenExpression.value": "#33333399",
        //"debugView.exceptionLabelBackground": "#6c2022",
        //"debugView.exceptionLabelForeground": "#333333",
        //"debugView.stateLabelBackground": "#88888844",
        //"debugView.stateLabelForeground": "#333333",
        //"debugView.valueChangedHighlight": "#003FE6",
        //"diffEditor.move.border": "#7474749c",
        //"diffEditor.moveActive.border": "#ffa500",
        //"diffEditor.unchangedCodeBackground": "#74747429",
        //"diffEditor.unchangedRegionBackground": "#E0E0E0",
        //"diffEditor.unchangedRegionForeground": "#333333",
        //"diffEditor.unchangedRegionShadow": "#000000",
        //"editor.compositionBorder": "#ffffff",
        //"editor.foldPlaceholderForeground": "#808080",
        //"editor.inactiveSelectionBackground": "#74747420",
        //"editor.inlineValuesBackground": "#ffc80033",
        //"editor.inlineValuesForeground": "#ffffff80",
        //"editor.linkedEditingBackground": "#ff00004d",
        //"editor.placeholder.foreground": "#ffffff56",
        //"editor.snippetFinalTabstopHighlightBorder": "#ADADAD",
        //"editor.snippetTabstopHighlightBackground": "#7c7c7c4d",
        //"editor.symbolHighlightBackground": "#3a4e55",
        //"editor.wordHighlightTextBackground": "#74747433",
        //"editorActionList.background": "#E0E0E0",
        //"editorActionList.focusBackground": "#D1D1D1",
        //"editorActionList.focusForeground": "#333333",
        //"editorActionList.foreground": "#333333",
        //"editorBracketPairGuide.activeBackground1": "#00000000",
        //"editorBracketPairGuide.activeBackground2": "#00000000",
        //"editorBracketPairGuide.activeBackground3": "#00000000",
        //"editorBracketPairGuide.activeBackground4": "#00000000",
        //"editorBracketPairGuide.activeBackground5": "#00000000",
        //"editorBracketPairGuide.activeBackground6": "#00000000",
        //"editorBracketPairGuide.background1": "#00000000",
        //"editorBracketPairGuide.background2": "#00000000",
        //"editorBracketPairGuide.background3": "#00000000",
        //"editorBracketPairGuide.background4": "#00000000",
        //"editorBracketPairGuide.background5": "#00000000",
        //"editorBracketPairGuide.background6": "#00000000",
        //"editorCommentsWidget.rangeActiveBackground": "#00000000",
        //"editorCommentsWidget.rangeBackground": "#00000000",
        //"editorCommentsWidget.replyInputBackground": "#E7E7E7",
        //"editorCommentsWidget.resolvedBorder": "#5F5F5F",
        //"editorCommentsWidget.unresolvedBorder": "#00000000",
        //"editorGhostText.foreground": "#ffffff56",
        //"editorGroup.dropIntoPromptBackground": "#E0E0E0",
        //"editorGroup.dropIntoPromptForeground": "#333333",
        //"editorGroupHeader.noTabsBackground": "#E7E7E7",
        //"editorGutter.commentUnresolvedGlyphForeground": "#9C9C9C",
        //"editorGutter.itemBackground": "#D1D1D1",
        //"editorGutter.itemGlyphForeground": "#333333",
        //"editorHint.foreground": "#eeeeeeb3",
        //"editorHoverWidget.highlightForeground": "#9C9C9C",
        //"editorHoverWidget.statusBarBackground": "#1d1d1d",
        // "editorIndentGuide.activeBackground2": "#00000000",
        // "editorIndentGuide.activeBackground3": "#00000000",
        // "editorIndentGuide.activeBackground4": "#00000000",
        // "editorIndentGuide.activeBackground5": "#00000000",
        // "editorIndentGuide.activeBackground6": "#00000000",
        // "editorIndentGuide.background2": "#00000000",
        // "editorIndentGuide.background3": "#00000000",
        // "editorIndentGuide.background4": "#00000000",
        // "editorIndentGuide.background5": "#00000000",
        // "editorIndentGuide.background6": "#00000000",
        //"editorLightBulbAi.foreground": "#DF8E1D",
        //"editorLightBulbAutoFix.foreground": "#75beff",
        //"editorMarkerNavigationError.headerBackground": "#C736001a",
        //"editorMarkerNavigationInfo.headerBackground": "#003FE61a",
        //"editorMarkerNavigationWarning.headerBackground": "#D85A101a",
        //"editorMinimap.inlineChatInserted": "#0071001f",
        //"editorMultiCursor.primary.background": null,
        "editorMultiCursor.primary.foreground": "#333333",
        //"editorMultiCursor.secondary.background": null,
        "editorMultiCursor.secondary.foreground": "#333333",
        //"editorOverviewRuler.addedForeground": "#00710099",
        //"editorOverviewRuler.bracketMatchForeground": "#5F5F5F",
        //"editorOverviewRuler.commentForeground": "#D1D1D1",
        //"editorOverviewRuler.commentUnresolvedForeground": "#D1D1D1",
        //"editorOverviewRuler.commonContentForeground": "#ADADAD",
        //"editorOverviewRuler.currentContentForeground": "#00710066",
        //"editorOverviewRuler.deletedForeground": "#C7360099",
        //"editorOverviewRuler.errorForeground": "#ff1212b3",
        //"editorOverviewRuler.findMatchForeground": "#d186167e",
        //"editorOverviewRuler.incomingContentForeground": "#003FE666",
        //"editorOverviewRuler.infoForeground": "#003FE6",
        //"editorOverviewRuler.inlineChatInserted": "#0071001f",
        //"editorOverviewRuler.inlineChatRemoved": "#C736001f",
        //"editorOverviewRuler.rangeHighlightForeground": "#007acc99",
        //"editorOverviewRuler.selectionHighlightForeground": "#5F5F5Fcc",
        //"editorOverviewRuler.warningForeground": "#D85A10",
        //"editorOverviewRuler.wordHighlightForeground": "#5F5F5Fcc",
        //"editorOverviewRuler.wordHighlightStrongForeground": "#c0a0c0cc",
        //"editorOverviewRuler.wordHighlightTextForeground": "#5F5F5Fcc",
        //"editorPane.background": "#E7E7E7",
        //"editorStickyScroll.background": "#E7E7E7",
        //"editorStickyScroll.shadow": "#E0E0E0",
        //"editorSuggestWidget.focusHighlightForeground": "#9C9C9C",
        //"editorSuggestWidget.selectedForeground": "#333333",
        //"editorSuggestWidgetStatus.foreground": "#33333380",
        //"editorUnicodeHighlight.background": "#00000000",
        //"editorUnicodeHighlight.border": "#D85A10",
        //"editorUnnecessaryCode.opacity": "#000000aa",
        //"editorWatermark.foreground": "#33333399",
        //"editorWidget.border": "#454545",
        //"extensionIcon.privateForeground": "#ffffff60",
        //"gauge.background": "#ECECEC33",
        //"gauge.errorBackground": "#ECECEC33",
        //"gauge.errorForeground": "#ECECEC0f",
        //"gauge.foreground": "#ECECEC0f",
        //"gauge.warningBackground": "#ECECEC33",
        //"gauge.warningForeground": "#ECECEC0f",
        //"git.blame.editorDecorationForeground": "#ADADAD",
        //"gitDecoration.renamedResourceForeground": "#73c991",
        //"inlineChat.background": "#E0E0E0",
        "inlineChat.border": "#00000000",
        //"inlineChat.foreground": "#333333",
        //"inlineChat.shadow": "#E0E0E080",
        //"inlineChatDiff.inserted": "#0071001a",
        //"inlineChatDiff.removed": "#C736001a",
        //"inlineChatInput.background": "#D1D1D1",
        //"inlineChatInput.border": "#454545",
        //"inlineChatInput.focusBorder": "#747474",
        //"inlineChatInput.placeholderForeground": "#5F5F5F",
        //"inlineEdit.gutterIndicator.background": "#E0E0E080",
        //"inlineEdit.gutterIndicator.primaryBackground": "#9C9C9C66",
        //"inlineEdit.gutterIndicator.primaryBorder": "#9C9C9C",
        //"inlineEdit.gutterIndicator.primaryForeground": "#333333",
        //"inlineEdit.gutterIndicator.secondaryBackground": "#ADADAD",
        //"inlineEdit.gutterIndicator.secondaryBorder": "#ADADAD",
        //"inlineEdit.gutterIndicator.secondaryForeground": "#333333",
        //"inlineEdit.gutterIndicator.successfulBackground": "#9C9C9C",
        //"inlineEdit.gutterIndicator.successfulBorder": "#9C9C9C",
        //"inlineEdit.gutterIndicator.successfulForeground": "#333333",
        //"inlineEdit.modifiedBackground": "#0071000f",
        //"inlineEdit.modifiedBorder": "#00710033",
        //"inlineEdit.modifiedChangedLineBackground": "#0071001b",
        //"inlineEdit.modifiedChangedTextBackground": "#00710024",
        //"inlineEdit.originalBackground": "#C736000a",
        //"inlineEdit.originalBorder": "#C7360033",
        //"inlineEdit.originalChangedLineBackground": "#C7360029",
        //"inlineEdit.originalChangedTextBackground": "#C7360029",
        //"inlineEdit.tabWillAcceptModifiedBorder": "#00710033",
        //"inlineEdit.tabWillAcceptOriginalBorder": "#db647433",
        //"inputOption.hoverBackground": "#5a5d5e80",
        //"interactive.activeCodeBorder": "#333333",
        //"interactive.inactiveCodeBorder": "#D1D1D1",
        //"keybindingLabel.background": "#8080802b",
        //"keybindingLabel.border": "#33333399",
        //"keybindingLabel.bottomBorder": "#44444499",
        //"keybindingLabel.foreground": "#333333",
        //"keybindingTable.headerBackground": "#3333330a",
        //"keybindingTable.rowsBackground": "#3333330a",
        //"list.deemphasizedForeground": "#8c8c8c",
        //"list.dropBetweenBackground": "#333333",
        //"list.errorForeground": "#f88070",
        //"list.filterMatchBackground": "#3a4e55",
        //"list.filterMatchBorder": "#04A5E533",
        //"list.focusHighlightForeground": "#9C9C9C",
        //"list.invalidItemForeground": "#b89500",
        //"listFilterWidget.shadow": "#E0E0E080",
        //"mergeEditor.change.background": "#9bb95533",
        //"mergeEditor.change.word.background": "#9ccc2c33",
        //"mergeEditor.changeBase.background": "#4b1818",
        //"mergeEditor.changeBase.word.background": "#6f1313",
        //"mergeEditor.conflict.handled.minimapOverViewRuler": "#adaca8ee",
        //"mergeEditor.conflict.handledFocused.border": "#c1c1c1cc",
        //"mergeEditor.conflict.handledUnfocused.border": "#86868649",
        //"mergeEditor.conflict.input1.background": "#00710029",
        //"mergeEditor.conflict.input2.background": "#003FE629",
        //"mergeEditor.conflict.unhandled.minimapOverViewRuler": "#fcba03",
        //"mergeEditor.conflict.unhandledFocused.border": "#ffa600",
        //"mergeEditor.conflict.unhandledUnfocused.border": "#ffa6007a",
        //"mergeEditor.conflictingLines.background": "#ffea0047",
        //"minimap.chatEditHighlight": "#E7E7E799",
        //"minimap.foregroundOpacity": "#000000",
        //"minimap.infoHighlight": "#003FE6",
        //"multiDiffEditor.background": "#E7E7E7",
        //"multiDiffEditor.headerBackground": "#262626",
        //"notebook.cellBorderColor": "#D1D1D1",
        //"notebook.cellEditorBackground": "#E0E0E0",
        //"notebook.cellInsertionIndicator": "#747474",
        //"notebook.cellStatusBarItemHoverBackground": "#ffffff26",
        //"notebook.cellToolbarSeparator": "#80808059",
        //"notebook.editorBackground": "#E7E7E7",
        //"notebook.focusedCellBorder": "#747474",
        //"notebook.focusedEditorBorder": "#747474",
        //"notebook.inactiveFocusedCellBorder": "#D1D1D1",
        //"notebook.selectedCellBackground": "#D1D1D1",
        //"notebook.selectedCellBorder": "#D1D1D1",
        //"notebook.symbolHighlightBackground": "#ffffff0b",
        //"notebookEditorOverviewRuler.runningCellForeground": "#007100",
        //"notebookScrollbarSlider.activeBackground": "#D1D1D166",
        //"notebookScrollbarSlider.background": "#ADADAD80",
        //"notebookScrollbarSlider.hoverBackground": "#9C9C9C",
        //"notebookStatusErrorIcon.foreground": "#C73600",
        //"notebookStatusRunningIcon.foreground": "#333333",
        //"notebookStatusSuccessIcon.foreground": "#007100",
        "panel.dropBorder": "#747474",
        //"panelInput.border": "#00000000",
        //"panelSectionHeader.background": "#80808033",
        //"panelStickyScroll.background": "#E0E0E0",
        //"panelStickyScroll.shadow": "#E0E0E0",
        //"panelTitleBadge.background": "#9C9C9C",
        //"panelTitleBadge.foreground": "#333333",
        //"peekViewEditorStickyScroll.background": "#E0E0E0",
        //"ports.iconRunningProcessForeground": "#9C9C9C",
        //"profileBadge.background": "#4d4d4d",
        //"profileBadge.foreground": "#ffffff",
        //"profiles.sashBorder": "#E7E7E7",
        //"quickInput.background": "#E0E0E0",
        //"quickInput.foreground": "#333333",
        //"quickInputList.focusBackground": "#D1D1D1",
        //"quickInputList.focusForeground": "#333333",
        //"quickInputTitle.background": "#ffffff1b",
        //"radio.activeBackground": "#ADADAD",
        //"radio.activeBorder": "#333333",
        //"radio.activeForeground": "#333333",
        //"radio.inactiveBorder": "#33333333",
        //"radio.inactiveHoverBackground": "#5a5d5e80",
        //"scmGraph.foreground1": "#ffb000",
        //"scmGraph.foreground2": "#dc267f",
        //"scmGraph.foreground3": "#994f00",
        //"scmGraph.foreground4": "#40b0a6",
        //"scmGraph.foreground5": "#b66dff",
        //"scmGraph.historyItemBaseRefColor": "#ea5c00",
        //"scmGraph.historyItemHoverAdditionsForeground": "#81b88b",
        //"scmGraph.historyItemHoverDefaultLabelBackground": "#C0C0C0",
        //"scmGraph.historyItemHoverDefaultLabelForeground": "#333333",
        //"scmGraph.historyItemHoverDeletionsForeground": "#c74e39",
        //"scmGraph.historyItemHoverLabelForeground": "#333333",
        //"scmGraph.historyItemRefColor": "#003FE6",
        //"scmGraph.historyItemRemoteRefColor": "#8839EF",
        //"search.resultsInfoForeground": "#333333a6",
        //"searchEditor.findMatchBackground": "#3a4e55a8",
        //"searchEditor.findMatchBorder": "#04A5E522",
        //"searchEditor.textInputBorder": "#00000000",
        //"settings.checkboxBackground": "#C0C0C0",
        //"settings.checkboxBorder": "#00000000",
        //"settings.checkboxForeground": "#9C9C9C",
        //"settings.dropdownBorder": "#747474",
        //"settings.dropdownForeground": "#333333",
        //"settings.focusedRowBorder": "#747474",
        //"settings.headerBorder": "#E7E7E7",
        //"settings.numberInputForeground": "#333333",
        //"settings.rowHoverBackground": "#D1D1D127",
        //"settings.sashBorder": "#E7E7E7",
        //"settings.settingsHeaderHoverForeground": "#333333b3",
        //"settings.textInputForeground": "#333333",
        //"sideBarStickyScroll.background": "#E0E0E0",
        //"sideBarStickyScroll.shadow": "#E0E0E0",
        //"sideBarTitle.background": "#E0E0E0",
        //"sideBySideEditor.horizontalBorder": "#ADADAD",
        //"sideBySideEditor.verticalBorder": "#ADADAD",
        //"simpleFindWidget.sashBorder": "#454545",
        "statusBar.focusBorder": "#747474",
        //"statusBarItem.compactHoverBackground": "#ffffff33",
        //"statusBarItem.errorHoverBackground": "#ADADAD33",
        //"statusBarItem.errorHoverForeground": "#333333",
        "statusBarItem.focusBorder": "#747474",
        //"statusBarItem.hoverForeground": "#333333",
        //"statusBarItem.offlineBackground": "#6c1717",
        //"statusBarItem.offlineForeground": "#333333",
        //"statusBarItem.offlineHoverBackground": "#ADADAD33",
        //"statusBarItem.offlineHoverForeground": "#333333",
        //"statusBarItem.prominentHoverForeground": "#333333",
        //"statusBarItem.remoteHoverForeground": "#333333",
        //"statusBarItem.warningHoverBackground": "#ADADAD33",
        //"statusBarItem.warningHoverForeground": "#333333",
        "tab.dragAndDropBorder": "#747474",
        //"tab.selectedBackground": "#E7E7E7",
        //"tab.selectedBorderTop": "#333333",
        //"tab.selectedForeground": "#333333",
        //"tab.unfocusedActiveModifiedBorder": "#003FE680",
        //"tab.unfocusedHoverBorder": "#00000000",
        //"tab.unfocusedInactiveModifiedBorder": "#003FE627",
        //"terminal.findMatchBackground": "#573438",
        //"terminal.findMatchHighlightBackground": "#3a4e55",
        //"terminal.hoverHighlightBackground": "#04A5E520",
        //"terminal.initialHintForeground": "#ffffff56",
        //"terminalCommandGuide.foreground": "#D1D1D1",
        //"terminalOverviewRuler.cursorForeground": "#5F5F5Fcc",
        //"terminalOverviewRuler.findMatchForeground": "#d186167e",
        //"terminalStickyScrollHover.background": "#2a2d2e",
        //"terminalSymbolIcon.aliasForeground": "#003FE6",
        //"terminalSymbolIcon.argumentForeground": "#333333",
        //"terminalSymbolIcon.fileForeground": "#333333",
        //"terminalSymbolIcon.flagForeground": "#DF8E1D",
        //"terminalSymbolIcon.folderForeground": "#333333",
        //"terminalSymbolIcon.methodForeground": "#003FE6",
        //"terminalSymbolIcon.optionForeground": "#DF8E1D",
        //"terminalSymbolIcon.optionValueForeground": "#DF8E1D",
        //"testing.message.error.badgeBackground": "#f14c4c",
        //"testing.message.error.badgeBorder": "#f14c4c",
        //"testing.message.error.badgeForeground": "#000000",
        //"textPreformat.background": "#ffffff1a",
        //"toolbar.activeBackground": "#63666750",
        //"toolbar.hoverBackground": "#5a5d5e50",
        //"tree.tableColumnsBorder": "#33333320",
        //"tree.tableOddRowsBackground": "#3333330a",
        //"walkthrough.stepTitle.foreground": "#ffffff",
        //"welcomePage.tileBorder": "#ffffff1a",
        //"welcomePage.tileHoverBackground": "#1d1d1d",
        //"activityBarTop.activeBackground": null,
        //"activityBarTop.background": null,
        //"contrastActiveBorder": null,
        //"contrastBorder": null,
        //"diffEditor.insertedTextBorder": null,
        //"diffEditor.removedTextBorder": null,
        //"diffEditorGutter.insertedLineBackground": null,
        //"diffEditorGutter.removedLineBackground": null,
        //"editor.findMatchForeground": null,
        //"editor.findMatchHighlightForeground": null,
        //"editor.selectionForeground": null,
        //"editor.snippetFinalTabstopHighlightBackground": null,
        //"editor.snippetTabstopHighlightBorder": null,
        //"editor.symbolHighlightBorder": null,
        //"editor.wordHighlightBorder": null,
        //"editor.wordHighlightStrongBorder": null,
        //"editor.wordHighlightTextBorder": null,
        //"editorGhostText.background": null,
        //"editorGhostText.border": null,
        //"editorGroup.dropIntoPromptBorder": null,
        //"editorGroup.focusedEmptyBorder": null,
        //"editorGroupHeader.border": null,
        //"editorGroupHeader.tabsBorder": null,
        //"editorHint.border": null,
        //"editorLineNumber.dimmedForeground": null,
        //"editorStickyScroll.border": null,
        //"editorSuggestWidget.selectedIconForeground": null,
        //"editorUnnecessaryCode.border": null,
        //"gauge.border": null,
        //"list.activeSelectionIconForeground": null,
        //"list.focusAndSelectionOutline": null,
        //"list.inactiveFocusBackground": null,
        //"list.inactiveFocusOutline": null,
        //"list.inactiveSelectionIconForeground": null,
        //"menubar.selectionBorder": null,
        //"merge.border": null,
        //"multiDiffEditor.border": null,
        //"notebook.cellHoverBackground": null,
        //"notebook.focusedCellBackground": null,
        //"notebook.inactiveSelectedCellBorder": null,
        //"notebook.outputContainerBackgroundColor": null,
        //"notebook.outputContainerBorderColor": null,
        //"outputView.background": null,
        //"outputViewStickyScroll.background": null,
        //"panelSectionHeader.border": null,
        //"panelSectionHeader.foreground": null,
        //"panelStickyScroll.border": null,
        //"panelTitle.border": null,
        //"quickInputList.focusIconForeground": null,
        //"radio.inactiveBackground": null,
        //"radio.inactiveForeground": null,
        //"sideBarActivityBarTop.border": null,
        //"sideBarSectionHeader.border": null,
        //"sideBarStickyScroll.border": null,
        //"sideBarTitle.border": null,
        //"terminal.background": null,
        //"terminal.findMatchBorder": null,
        //"terminal.findMatchHighlightBorder": null,
        //"terminal.selectionForeground": null,
        //"terminalStickyScroll.background": null,
        //"terminalStickyScroll.border": null,
        //"terminalSymbolIcon.inlineSuggestionForeground": null,
        //"toolbar.hoverOutline": null,
        //"welcomePage.background": null,
        //"widget.border": null
    }
}
